LICENSE
MANIFEST.in
README.rst
setup.cfg
setup.py
ctlimit/__init__.py
ctlimit/__main__.py
ctlimit/_impl.py
ctlimit/ctlimit.conf
ctlimit/ctlimit.service
ctlimit/ctlimit_default.conf
ctlimit/de.kruis.ctlimit1.conf
ctlimit/logout_X11.bash
ctlimit/sddaemon.py
ctlimit/test.py
ctlimit/test_sddaemon.py
ctlimit.egg-info/PKG-INFO
ctlimit.egg-info/SOURCES.txt
ctlimit.egg-info/dependency_links.txt
ctlimit.egg-info/entry_points.txt
ctlimit.egg-info/requires.txt
ctlimit.egg-info/top_level.txt
ctlimit/spi/__init__.py
ctlimit/spi/logind.py
ctlimit/spi/test_logind.py
doc/conf.py
doc/index.rst