Metadata-Version: 1.1
Name: ctlimit
Version: 0.0.5
Summary: Computer Time Limit for Children
Home-page: https://bitbucket.org/akruis/ctlimit
Author: Esther and Anselm Kruis
Author-email: ctlimit@kruis.de
License: LGPLv2+
Keywords: desktop parental-control
Platform: UNKNOWN
Classifier: Development Status :: 3 - Alpha
Classifier: Intended Audience :: End Users/Desktop
Classifier: Natural Language :: German
Classifier: Topic :: Desktop Environment
Classifier: Topic :: Utilities
Classifier: License :: OSI Approved :: GNU Lesser General Public License v2 or later (LGPLv2+)
Classifier: Programming Language :: Python :: 3.4
Classifier: Programming Language :: Python :: 3.5
Classifier: Environment :: No Input/Output (Daemon)
Classifier: Operating System :: POSIX :: Linux
